libhockey/__init__.py
libhockey/constants.py
libhockey/crashes.py
libhockey/derived_client.py
libhockey/versions.py
libhockey-0.23.0.dist-info/LICENSE
libhockey-0.23.0.dist-info/WHEEL
libhockey-0.23.0.dist-info/METADATA
libhockey-0.23.0.dist-info/RECORD
