Metadata-Version: 2.1
Name: libhockey
Version: 0.23.0
Summary: A Python wrapper around the Hockey App API.
Home-page: https://github.com/Microsoft/libhockey
License: MIT
Keywords: hockey,hockeyapp,api
Author: Dale Myers
Author-email: dalemy@microsoft.com
Requires-Python: >=3.6,<4.0
Classifier: Development Status :: 7 - Inactive
Classifier: Intended Audience :: Developers
Classifier: License :: OSI Approved :: MIT License
Classifier: Programming Language :: Python :: 3
Classifier: Programming Language :: Python :: 3.6
Classifier: Programming Language :: Python :: 3.7
Classifier: Topic :: Software Development
Classifier: Topic :: Utilities
Requires-Dist: deserialize (>=1,<2)
Requires-Dist: requests (>=2.22.0,<3.0.0)
Project-URL: Repository, https://github.com/Microsoft/libhockey
